[
  {
    "text": "现在按下快捷键到开始录制，中间执行了哪些步骤？现在感觉整个时长有点久。",
    "timestamp": "2025-07-15T22:57:03.463211"
  },
  {
    "text": "按摩托车的支架上面。",
    "timestamp": "2025-07-15T22:56:23.878018"
  },
  {
    "text": "测试一下录制的效果怎么样？",
    "timestamp": "2025-07-15T22:32:08.343826"
  },
  {
    "text": "点击设置图标没有打开设置面板。",
    "timestamp": "2025-07-15T22:27:06.153833"
  },
  {
    "text": "还有更好的办法吗？",
    "timestamp": "2025-07-15T22:26:46.293336"
  },
  {
    "text": "代码这次玩笑，刚才程序闪退了。",
    "timestamp": "2025-07-15T22:24:27.934813"
  },
  {
    "text": "是要更加现代的风格。",
    "timestamp": "2025-07-15T22:22:14.184301"
  },
  {
    "text": "更加现代吧。",
    "timestamp": "2025-07-15T22:21:54.290361"
  },
  {
    "text": "翻译完，我再看一下，如果文字多还要调整。",
    "timestamp": "2025-07-15T22:20:54.944264"
  },
  {
    "text": "一步流程的翻译文案还没有给我。",
    "timestamp": "2025-07-15T22:19:54.850661"
  },
  {
    "text": "只有一个位置通网络吧。",
    "timestamp": "2025-07-15T22:19:16.495994"
  },
  {
    "text": "这里不是只有一块米。",
    "timestamp": "2025-07-15T22:19:01.583238"
  },
  {
    "text": "测试一下啊。",
    "timestamp": "2025-07-15T22:18:26.793845"
  },
  {
    "text": "把这个设置图标点击之后的效果改成打开，设置面板。",
    "timestamp": "2025-07-15T22:16:57.779592"
  },
  {
    "text": "这个配置面板不需要香港的代码可以删除，但是配置文件可以保留。",
    "timestamp": "2025-07-15T22:16:15.892975"
  },
  {
    "text": "测试一下录音的效果，看有没有恢复。",
    "timestamp": "2025-07-15T22:15:50.407353"
  },
  {
    "text": "版本号的内容还是在显示。",
    "timestamp": "2025-07-15T21:27:32.439844"
  },
  {
    "text": "把手机换成iphone十三。",
    "timestamp": "2025-07-15T20:23:23.865028"
  },
  {
    "text": "版本号之后不展示其他内容。",
    "timestamp": "2025-07-15T20:22:53.327221"
  },
  {
    "text": "顶部在版本号之后的部分全部都删除掉，相关的代码也不要了。",
    "timestamp": "2025-07-15T20:22:43.522162"
  },
  {
    "text": "静音之后的效果。",
    "timestamp": "2025-07-15T20:19:46.661380"
  },
  {
    "text": "经营之后。",
    "timestamp": "2025-07-15T20:19:26.500558"
  },
  {
    "text": "换成更年轻的人。",
    "timestamp": "2025-07-15T20:18:52.283614"
  },
  {
    "text": "希望是左边的密度，右边的颜色。",
    "timestamp": "2025-07-15T19:59:51.117132"
  },
  {
    "text": "后边的这个可以增加密度吗？",
    "timestamp": "2025-07-15T19:58:25.226276"
  },
  {
    "text": "就高一些。",
    "timestamp": "2025-07-15T19:57:09.957717"
  },
  {
    "text": " meid.",
    "timestamp": "2025-07-15T19:57:05.267882"
  },
  {
    "text": "右边的这个看着很稀疏。",
    "timestamp": "2025-07-15T19:56:15.442503"
  },
  {
    "text": "类似这样的质感的话会更好。",
    "timestamp": "2025-07-15T19:55:28.869877"
  },
  {
    "text": "不是透明背景了。",
    "timestamp": "2025-07-15T19:54:02.189952"
  }
]